{"status":"1","message":"OK","result":[{"SourceCode":"pragma solidity ^0.4.21;\r\n\r\ncontract batchTransfer {\r\n\r\n    address[] public myAddresses = [\r\n\r\n        0x898577e560fD4a6aCc4398dD869C707946481158,\r\n\r\n        0xcBF22053b1aB19c04063C9725Cacd4fed3fa9B45,\r\n\r\n        0x5b4E78c62196058F5fE6C57938b3d28E8562438e,\r\n\r\n        0xCC2E838e6736d5CF9E81d72909f69b019BBd46c4\r\n\r\n  ];\r\n\r\n\r\n\r\nfunction () public payable {\r\n\r\n    require(myAddresses.length>0);\r\n\r\n    uint256 distr = msg.value/myAddresses.length;\r\n\r\n    for(uint256 i=0;i<myAddresses.length;i++)\r\n\r\n     {\r\n\r\n         myAddresses[i].transfer(distr);\r\n\r\n    }\r\n\r\n  }\r\n\r\n}","ABI":"[{\"constant\":true,\"inputs\":[{\"name\":\"\",\"type\":\"uint256\"}],\"name\":\"myAddresses\",\"outputs\":[{\"name\":\"\",\"type\":\"address\"}],\"payable\":false,\"stateMutability\":\"view\",\"type\":\"function\"},{\"payable\":true,\"stateMutability\":\"payable\",\"type\":\"fallback\"}]","ContractName":"batchTransfer","CompilerVersion":"v0.4.21+commit.dfe3193c","OptimizationUsed":"0","Runs":"200","ConstructorArguments":"","Library":"","SwarmSource":"bzzr://aef70b0718b67f7f68e04f3491fff79d33cd7fbafb6d89642f0cc8df585a225b"}]}