{"status":"1","message":"OK","result":[{"SourceCode":"pragma solidity ^0.5.16;\r\n\r\ncontract ERC20Basic {\r\n\r\n    function balanceOf(address tokenOwner) external view returns (uint balance);\r\n    function allowance(address tokenOwner, address spender) external view returns (uint remaining);\r\n    function approve(address spender, uint tokens) external returns (bool success);\r\n\r\n    function transfer(address to, uint tokens) external returns (bool success);\r\n    function transferFrom(address from, address to, uint tokens) public returns (bool success);\r\n    \r\n    event Transfer(address indexed from, address indexed to, uint tokens);\r\n    event Approval(address indexed tokenOwner, address indexed spender, uint tokens);\r\n}\r\n\r\ncontract MyERC20 is ERC20Basic {\r\n\r\n    string public  name;\r\n    string public  symbol;\r\n    uint8 public constant decimals = 18;\r\n    uint public totalSupply;\r\n    mapping(address => uint256) internal _balances;\r\n    mapping(address => mapping(address => uint256)) allowed;\r\n\r\n    constructor(string memory _name, string memory _symbol, uint256 _initialSupply) public {\r\n       name = _name;\r\n       symbol = _symbol;\r\n       totalSupply = sftotalSupply(_initialSupply);\r\n       _balances[msg.sender] = totalSupply;\r\n    }\r\n\r\n    function balanceOf(address tokenOwner) public view returns (uint balance) {\r\n        return _balances[tokenOwner];\r\n    }\r\n\r\n    function allowance(address _owner, address _spender) public view returns (uint256 remaining) {\r\n        return allowed[_owner][_spender];\r\n    }\r\n    \r\n    function sftotalSupply(uint256 _vla) public view returns (uint256 totalval) {\r\n        return _vla * 10 ** uint256(decimals);\r\n    }\r\n  \r\n    function transferFrom(address _from, address _to, uint256 _value) public returns (bool success) {\r\n        require(_to != address(0));\r\n        require(allowed[_from][msg.sender] >= _value);\r\n        require(_balances[_from] >= _value);\r\n        require(_balances[ _to] + _value >= _balances[ _to]);\r\n        _balances[_from] -= _value;\r\n        _balances[_to] += _value;\r\n        allowed[_from][msg.sender] -= _value;\r\n        emit Transfer(msg.sender, _to, _value);\r\n        return true;\r\n    }\r\n\r\n    function transfer(address _to, uint256 _value)  public returns (bool success) {\r\n        require(_to != address(0));\r\n        require(_balances[msg.sender] >= _value);\r\n        require(_balances[ _to] + _value >= _balances[ _to]);\r\n        _balances[msg.sender] -= _value;\r\n        _balances[_to] += _value;\r\n        emit Transfer(msg.sender, _to, _value);\r\n        return true;\r\n    }\r\n\r\n    function approve(address _spender, uint256 _value) public returns (bool success) {\r\n      allowed[msg.sender][_spender] = _value;\r\n      emit Approval(msg.sender, _spender, _value);\r\n      return true;\r\n    }\r\n\r\n}","ABI":"[{\"inputs\":[{\"internalType\":\"string\",\"name\":\"_name\",\"type\":\"string\"},{\"internalType\":\"string\",\"name\":\"_symbol\",\"type\":\"string\"},{\"internalType\":\"uint256\",\"name\":\"_initialSupply\",\"type\":\"uint256\"}],\"payable\":false,\"stateMutability\":\"nonpayable\",\"type\":\"constructor\"},{\"anonymous\":false,\"inputs\":[{\"indexed\":true,\"internalType\":\"address\",\"name\":\"tokenOwner\",\"type\":\"address\"},{\"indexed\":true,\"internalType\":\"address\",\"name\":\"spender\",\"type\":\"address\"},{\"indexed\":false,\"internalType\":\"uint256\",\"name\":\"tokens\",\"type\":\"uint256\"}],\"name\":\"Approval\",\"type\":\"event\"},{\"anonymous\":false,\"inputs\":[{\"indexed\":true,\"internalType\":\"address\",\"name\":\"from\",\"type\":\"address\"},{\"indexed\":true,\"internalType\":\"address\",\"name\":\"to\",\"type\":\"address\"},{\"indexed\":false,\"internalType\":\"uint256\",\"name\":\"tokens\",\"type\":\"uint256\"}],\"name\":\"Transfer\",\"type\":\"event\"},{\"constant\":true,\"inputs\":[{\"internalType\":\"address\",\"name\":\"_owner\",\"type\":\"address\"},{\"internalType\":\"address\",\"name\":\"_spender\",\"type\":\"address\"}],\"name\":\"allowance\",\"outputs\":[{\"internalType\":\"uint256\",\"name\":\"remaining\",\"type\":\"uint256\"}],\"payable\":false,\"stateMutability\":\"view\",\"type\":\"function\"},{\"constant\":false,\"inputs\":[{\"internalType\":\"address\",\"name\":\"_spender\",\"type\":\"address\"},{\"internalType\":\"uint256\",\"name\":\"_value\",\"type\":\"uint256\"}],\"name\":\"approve\",\"outputs\":[{\"internalType\":\"bool\",\"name\":\"success\",\"type\":\"bool\"}],\"payable\":false,\"stateMutability\":\"nonpayable\",\"type\":\"function\"},{\"constant\":true,\"inputs\":[{\"internalType\":\"address\",\"name\":\"tokenOwner\",\"type\":\"address\"}],\"name\":\"balanceOf\",\"outputs\":[{\"internalType\":\"uint256\",\"name\":\"balance\",\"type\":\"uint256\"}],\"payable\":false,\"stateMutability\":\"view\",\"type\":\"function\"},{\"constant\":true,\"inputs\":[],\"name\":\"decimals\",\"outputs\":[{\"internalType\":\"uint8\",\"name\":\"\",\"type\":\"uint8\"}],\"payable\":false,\"stateMutability\":\"view\",\"type\":\"function\"},{\"constant\":true,\"inputs\":[],\"name\":\"name\",\"outputs\":[{\"internalType\":\"string\",\"name\":\"\",\"type\":\"string\"}],\"payable\":false,\"stateMutability\":\"view\",\"type\":\"function\"},{\"constant\":true,\"inputs\":[{\"internalType\":\"uint256\",\"name\":\"_vla\",\"type\":\"uint256\"}],\"name\":\"sftotalSupply\",\"outputs\":[{\"internalType\":\"uint256\",\"name\":\"totalval\",\"type\":\"uint256\"}],\"payable\":false,\"stateMutability\":\"view\",\"type\":\"function\"},{\"constant\":true,\"inputs\":[],\"name\":\"symbol\",\"outputs\":[{\"internalType\":\"string\",\"name\":\"\",\"type\":\"string\"}],\"payable\":false,\"stateMutability\":\"view\",\"type\":\"function\"},{\"constant\":true,\"inputs\":[],\"name\":\"totalSupply\",\"outputs\":[{\"internalType\":\"uint256\",\"name\":\"\",\"type\":\"uint256\"}],\"payable\":false,\"stateMutability\":\"view\",\"type\":\"function\"},{\"constant\":false,\"inputs\":[{\"internalType\":\"address\",\"name\":\"_to\",\"type\":\"address\"},{\"internalType\":\"uint256\",\"name\":\"_value\",\"type\":\"uint256\"}],\"name\":\"transfer\",\"outputs\":[{\"internalType\":\"bool\",\"name\":\"success\",\"type\":\"bool\"}],\"payable\":false,\"stateMutability\":\"nonpayable\",\"type\":\"function\"},{\"constant\":false,\"inputs\":[{\"internalType\":\"address\",\"name\":\"_from\",\"type\":\"address\"},{\"internalType\":\"address\",\"name\":\"_to\",\"type\":\"address\"},{\"internalType\":\"uint256\",\"name\":\"_value\",\"type\":\"uint256\"}],\"name\":\"transferFrom\",\"outputs\":[{\"internalType\":\"bool\",\"name\":\"success\",\"type\":\"bool\"}],\"payable\":false,\"stateMutability\":\"nonpayable\",\"type\":\"function\"}]","ContractName":"MyERC20","CompilerVersion":"v0.5.16+commit.9c3226ce","OptimizationUsed":"0","Runs":"200","ConstructorArguments":"000000000000000000000000000000000000000000000000000000000000006000000000000000000000000000000000000000000000000000000000000000a0000000000000000000000000000000000000000000000000000000001dcd65000000000000000000000000000000000000000000000000000000000000000007504e4e55303031000000000000000000000000000000000000000000000000000000000000000000000000000000000000000000000000000000000000000007504e4e5530303100000000000000000000000000000000000000000000000000","Library":"","LicenseType":"None","SwarmSource":"bzzr://bf97d2dc43bb1ed16a2475139389fbd029df985ccf55bc0d6941ef4c90b59d6c"}]}