{"status":"1","message":"OK","result":[{"SourceCode":"// SPDX-License-Identifier: MIT\r\n\r\npragma solidity ^0.8.0;\r\n\r\n\r\ninterface MapContract {\r\n    function discoverMap(uint256 tokenId) external;\r\n    function safeTransferFrom(address from, address to, uint256 tokenId) external;\r\n}\r\n\r\n\r\ninterface IERC721Receiver {\r\n    /**\r\n     * @dev Whenever an {IERC721} `tokenId` token is transferred to this contract via {IERC721-safeTransferFrom}\r\n     * by `operator` from `from`, this function is called.\r\n     *\r\n     * It must return its Solidity selector to confirm the token transfer.\r\n     * If any other value is returned or the interface is not implemented by the recipient, the transfer will be reverted.\r\n     *\r\n     * The selector can be obtained in Solidity with `IERC721.onERC721Received.selector`.\r\n     */\r\n    function onERC721Received(\r\n        address operator,\r\n        address from,\r\n        uint256 tokenId,\r\n        bytes calldata data\r\n    ) external returns (bytes4);\r\n}\r\n\r\ncontract MultiMap is IERC721Receiver {\r\n    \r\n    \r\n    MapContract _lootContract = MapContract(0xD81f156bBF7043a22d4cE97C0E8ca11d3f4FB3cC);\r\n    \r\n    function getMultiLoot(uint256 numberToMint) public {\r\n    \r\n        uint256 mintedAmount = 0;\r\n        \r\n        for (uint i = 0; i < 9751; i++) {\r\n            if (mintedAmount >= numberToMint) {\r\n                break;\r\n            }\r\n            try _lootContract.discoverMap(i) {\r\n                _lootContract.safeTransferFrom(address(this), msg.sender, i);\r\n                mintedAmount++;\r\n            } catch {}\r\n        }\r\n    }\r\n    \r\n     function onERC721Received(address, address, uint256, bytes memory) public virtual override returns (bytes4) {\r\n        return this.onERC721Received.selector;\r\n    }\r\n    \r\n    \r\n    \r\n}","ABI":"[{\"inputs\":[{\"internalType\":\"uint256\",\"name\":\"numberToMint\",\"type\":\"uint256\"}],\"name\":\"getMultiLoot\",\"outputs\":[],\"stateMutability\":\"nonpayable\",\"type\":\"function\"},{\"inputs\":[{\"internalType\":\"address\",\"name\":\"\",\"type\":\"address\"},{\"internalType\":\"address\",\"name\":\"\",\"type\":\"address\"},{\"internalType\":\"uint256\",\"name\":\"\",\"type\":\"uint256\"},{\"internalType\":\"bytes\",\"name\":\"\",\"type\":\"bytes\"}],\"name\":\"onERC721Received\",\"outputs\":[{\"internalType\":\"bytes4\",\"name\":\"\",\"type\":\"bytes4\"}],\"stateMutability\":\"nonpayable\",\"type\":\"function\"}]","ContractName":"MultiMap","CompilerVersion":"v0.8.6+commit.11564f7e","OptimizationUsed":"1","Runs":"200","ConstructorArguments":"","EVMVersion":"Default","Library":"","LicenseType":"MIT","Proxy":"0","Implementation":"","SwarmSource":"ipfs://2a4186f7abce257b0b18c08546d9ec421e225fc17148cb1f6bcf4a8179cc7e80"}]}