{"status":"1","message":"OK","result":[{"SourceCode":"pragma solidity ^0.5.16;\r\n\r\ninterface IFeed {\r\n    function decimals() external view returns (uint8);\r\n    function latestAnswer() external view returns (uint);\r\n}\r\n\r\ncontract DolaFeed is IFeed {\r\n\r\n    function decimals() public view returns(uint8) {\r\n        return 18;\r\n    }\r\n\r\n    function latestAnswer() public view returns (uint) {\r\n        return 1 ether;\r\n    }\r\n\r\n}","ABI":"[{\"constant\":true,\"inputs\":[],\"name\":\"decimals\",\"outputs\":[{\"internalType\":\"uint8\",\"name\":\"\",\"type\":\"uint8\"}],\"payable\":false,\"stateMutability\":\"view\",\"type\":\"function\"},{\"constant\":true,\"inputs\":[],\"name\":\"latestAnswer\",\"outputs\":[{\"internalType\":\"uint256\",\"name\":\"\",\"type\":\"uint256\"}],\"payable\":false,\"stateMutability\":\"view\",\"type\":\"function\"}]","ContractName":"DolaFeed","CompilerVersion":"v0.5.16+commit.9c3226ce","OptimizationUsed":"1","Runs":"200","ConstructorArguments":"","EVMVersion":"Default","Library":"","LicenseType":"None","Proxy":"0","Implementation":"","SwarmSource":"bzzr://b8909dd45b9db4bfbedb95f8cefb3fa8bcbb173e760288cf53c03a58e688f201"}]}