{"status":"1","message":"OK","result":[{"SourceCode":"pragma solidity ^0.4.15;\r\ncontract theRiver{\r\n\tfunction() external payable { }\r\n}","ABI":"[{\"payable\":true,\"type\":\"fallback\"}]","ContractName":"theRiver","CompilerVersion":"v0.4.15+commit.bbb8e64f","OptimizationUsed":"0","Runs":"200","ConstructorArguments":"","EVMVersion":"Default","Library":"","LicenseType":"None","Proxy":"0","Implementation":"","SwarmSource":"bzzr://8a6ab91be9fc7c739f7132443a5608ac0a8446f331835070f5455e6bbd8bc5f5"}]}