{"status":"1","message":"OK","result":[{"SourceCode":"pragma solidity ^0.4.24;\r\n\r\ninterface FoMo3DlongInterface {\r\n      function getBuyPrice()\r\n        public\r\n        view\r\n        returns(uint256)\r\n    ;\r\n  function getTimeLeft()\r\n        public\r\n        view\r\n        returns(uint256)\r\n    ;\r\n  function withdraw() external;\r\n}\r\n\r\ncontract Owned {\r\n    address public owner;\r\n    address public newOwner;\r\n\r\n    event OwnershipTransferred(address indexed _from, address indexed _to);\r\n\r\n    function Owned() public {\r\n        owner = msg.sender;\r\n    }\r\n\r\n    modifier onlyOwner {\r\n        require(msg.sender == owner);\r\n        _;\r\n    }\r\n\r\n    function transferOwnership(address _newOwner) public onlyOwner {\r\n        newOwner = _newOwner;\r\n    }\r\n    \r\n    function acceptOwnership() public {\r\n        require(msg.sender == newOwner);\r\n        emit OwnershipTransferred(owner, newOwner);\r\n        owner = newOwner;\r\n        newOwner = address(0);\r\n    }\r\n}\r\n\r\ncontract PwnFoMo3D is Owned {\r\n    FoMo3DlongInterface fomo3d;\r\n  constructor() public payable {\r\n     fomo3d  = FoMo3DlongInterface(0x0aD3227eB47597b566EC138b3AfD78cFEA752de5);\r\n  }\r\n  \r\n  function gotake() public  {\r\n    // Link up the fomo3d contract and ensure this whole thing is worth it\r\n    \r\n    // if (fomo3d.getTimeLeft() > 50) {\r\n    //   revert();\r\n    // }\r\n\r\n    address(fomo3d).call.value( fomo3d.getBuyPrice() *2 )();\r\n  }\r\n  \r\n     function withdrawOwner2(uint256 a)  public onlyOwner {\r\n        fomo3d.withdraw();\r\n    }\r\n  \r\n    function withdrawOwner(uint256 a)  public onlyOwner {\r\n        msg.sender.transfer(a);    \r\n    }\r\n}","ABI":"[{\"constant\":false,\"inputs\":[{\"name\":\"a\",\"type\":\"uint256\"}],\"name\":\"withdrawOwner\",\"outputs\":[],\"payable\":false,\"stateMutability\":\"nonpayable\",\"type\":\"function\"},{\"constant\":false,\"inputs\":[],\"name\":\"acceptOwnership\",\"outputs\":[],\"payable\":false,\"stateMutability\":\"nonpayable\",\"type\":\"function\"},{\"constant\":true,\"inputs\":[],\"name\":\"owner\",\"outputs\":[{\"name\":\"\",\"type\":\"address\"}],\"payable\":false,\"stateMutability\":\"view\",\"type\":\"function\"},{\"constant\":false,\"inputs\":[{\"name\":\"a\",\"type\":\"uint256\"}],\"name\":\"withdrawOwner2\",\"outputs\":[],\"payable\":false,\"stateMutability\":\"nonpayable\",\"type\":\"function\"},{\"constant\":true,\"inputs\":[],\"name\":\"newOwner\",\"outputs\":[{\"name\":\"\",\"type\":\"address\"}],\"payable\":false,\"stateMutability\":\"view\",\"type\":\"function\"},{\"constant\":false,\"inputs\":[],\"name\":\"gotake\",\"outputs\":[],\"payable\":false,\"stateMutability\":\"nonpayable\",\"type\":\"function\"},{\"constant\":false,\"inputs\":[{\"name\":\"_newOwner\",\"type\":\"address\"}],\"name\":\"transferOwnership\",\"outputs\":[],\"payable\":false,\"stateMutability\":\"nonpayable\",\"type\":\"function\"},{\"inputs\":[],\"payable\":true,\"stateMutability\":\"payable\",\"type\":\"constructor\"},{\"anonymous\":false,\"inputs\":[{\"indexed\":true,\"name\":\"_from\",\"type\":\"address\"},{\"indexed\":true,\"name\":\"_to\",\"type\":\"address\"}],\"name\":\"OwnershipTransferred\",\"type\":\"event\"}]","ContractName":"PwnFoMo3D","CompilerVersion":"v0.4.24+commit.e67f0147","OptimizationUsed":"1","Runs":"200","ConstructorArguments":"","Library":"","SwarmSource":"bzzr://a67653cdf196f358800947b83c146404c0bc1029d089ef2543b8cf311d5caeff"}]}