{"status":"1","message":"OK","result":[{"SourceCode":"pragma solidity ^0.4.24;\r\n\r\n\r\ncontract Ownable {\r\n  address public owner;\r\n\r\n  /**\r\n   * @dev The Ownable constructor sets the original `owner` of the contract to the sender\r\n   * account.\r\n   */\r\n  constructor() public {\r\n    owner = msg.sender;\r\n  }\r\n\r\n\r\n  /**\r\n   * @dev Throws if called by any account other than the owner.\r\n   */\r\n  modifier onlyOwner() {\r\n    require(msg.sender == owner);\r\n    _;\r\n  }\r\n\r\n\r\n  /**\r\n   * @dev Allows the current owner to transfer control of the contract to a newOwner.\r\n   * @param newOwner The address to transfer ownership to.\r\n   */\r\n  function transferOwnership(address newOwner) public onlyOwner {\r\n    if (newOwner != address(0)) {\r\n      owner = newOwner;\r\n    }\r\n  }\r\n\r\n}\r\n\r\n\r\ncontract HelpingBlocksContract is Ownable {\r\n    string public name;\r\n    string public symbol;\r\n    uint public decimals;\r\n    uint public totalSupply;\r\n    string public description;\r\n    bool public donationClosed = false;\r\n\r\n    mapping (address => uint256) public balanceOf;\r\n    /* To track donated amount of a user */\r\n    mapping (address => uint256) public myDonation;\r\n    event Transfer(address indexed from, address indexed to, uint256 value);\r\n\r\n\r\n    /**\r\n     * Constructor function\r\n     *\r\n     * Initializes contract with initial supply tokens to the creator of the contract\r\n     */\r\n    constructor() public {\r\n        name = 'Helping Blocks Token';\r\n        symbol = 'HBT';\r\n        decimals = 0;\r\n        totalSupply = 10000000;\r\n        description = \"Kerala Flood Relief Fund\";\r\n        balanceOf[owner] = totalSupply;\r\n    }\r\n\r\n    /**\r\n     * Internal transfer, only can be called by this contract\r\n     */\r\n    function _transfer(address _from, address _to, uint _value) internal {\r\n        balanceOf[_from] -= _value;\r\n        balanceOf[_to] += _value;\r\n        emit Transfer(_from, _to, _value);\r\n    }\r\n\r\n    /**\r\n     * Transfer tokens\r\n     *\r\n     * Send `_value` tokens to `_to` from your account\r\n     *\r\n     * @param _to The address of the recipient\r\n     * @param _value the amount to send\r\n     */\r\n    function transfer(address _to, uint256 _value) public onlyOwner returns(bool success) {\r\n        _transfer(owner, _to, _value);\r\n        return true;\r\n    }\r\n\r\n    /* Stop taking donations */\r\n    function disableDonation() public onlyOwner returns(bool success) {\r\n      donationClosed = true;\r\n      return true;\r\n    }\r\n\r\n\r\n    /* Start taking donations */\r\n    function enableDonation() public onlyOwner returns(bool success) {\r\n      donationClosed = false;\r\n      return true;\r\n    }\r\n\r\n    function setDescription(string str) public onlyOwner returns(bool success) {\r\n      description = str;\r\n      return true;\r\n    }\r\n\r\n\r\n    /**\r\n     * Fallback function\r\n     *\r\n     * The function without name is the default function that is called whenever anyone sends funds to a contract\r\n     */\r\n    function () payable public {\r\n      require(!donationClosed);\r\n      myDonation[msg.sender] += msg.value;\r\n      if (balanceOf[msg.sender] < 1) {\r\n        _transfer(owner, msg.sender, 1);\r\n      }\r\n    }\r\n\r\n    function safeWithdrawal(uint256 _value) payable public onlyOwner {\r\n      owner.transfer(_value);\r\n    }\r\n}","ABI":"[{\"constant\":true,\"inputs\":[],\"name\":\"name\",\"outputs\":[{\"name\":\"\",\"type\":\"string\"}],\"payable\":false,\"stateMutability\":\"view\",\"type\":\"function\"},{\"constant\":true,\"inputs\":[],\"name\":\"totalSupply\",\"outputs\":[{\"name\":\"\",\"type\":\"uint256\"}],\"payable\":false,\"stateMutability\":\"view\",\"type\":\"function\"},{\"constant\":true,\"inputs\":[],\"name\":\"decimals\",\"outputs\":[{\"name\":\"\",\"type\":\"uint256\"}],\"payable\":false,\"stateMutability\":\"view\",\"type\":\"function\"},{\"constant\":false,\"inputs\":[{\"name\":\"_value\",\"type\":\"uint256\"}],\"name\":\"safeWithdrawal\",\"outputs\":[],\"payable\":true,\"stateMutability\":\"payable\",\"type\":\"function\"},{\"constant\":true,\"inputs\":[{\"name\":\"\",\"type\":\"address\"}],\"name\":\"balanceOf\",\"outputs\":[{\"name\":\"\",\"type\":\"uint256\"}],\"payable\":false,\"stateMutability\":\"view\",\"type\":\"function\"},{\"constant\":true,\"inputs\":[],\"name\":\"description\",\"outputs\":[{\"name\":\"\",\"type\":\"string\"}],\"payable\":false,\"stateMutability\":\"view\",\"type\":\"function\"},{\"constant\":true,\"inputs\":[],\"name\":\"owner\",\"outputs\":[{\"name\":\"\",\"type\":\"address\"}],\"payable\":false,\"stateMutability\":\"view\",\"type\":\"function\"},{\"constant\":true,\"inputs\":[{\"name\":\"\",\"type\":\"address\"}],\"name\":\"myDonation\",\"outputs\":[{\"name\":\"\",\"type\":\"uint256\"}],\"payable\":false,\"stateMutability\":\"view\",\"type\":\"function\"},{\"constant\":false,\"inputs\":[{\"name\":\"str\",\"type\":\"string\"}],\"name\":\"setDescription\",\"outputs\":[{\"name\":\"success\",\"type\":\"bool\"}],\"payable\":false,\"stateMutability\":\"nonpayable\",\"type\":\"function\"},{\"constant\":true,\"inputs\":[],\"name\":\"symbol\",\"outputs\":[{\"name\":\"\",\"type\":\"string\"}],\"payable\":false,\"stateMutability\":\"view\",\"type\":\"function\"},{\"constant\":false,\"inputs\":[],\"name\":\"enableDonation\",\"outputs\":[{\"name\":\"success\",\"type\":\"bool\"}],\"payable\":false,\"stateMutability\":\"nonpayable\",\"type\":\"function\"},{\"constant\":false,\"inputs\":[{\"name\":\"_to\",\"type\":\"address\"},{\"name\":\"_value\",\"type\":\"uint256\"}],\"name\":\"transfer\",\"outputs\":[{\"name\":\"success\",\"type\":\"bool\"}],\"payable\":false,\"stateMutability\":\"nonpayable\",\"type\":\"function\"},{\"constant\":true,\"inputs\":[],\"name\":\"donationClosed\",\"outputs\":[{\"name\":\"\",\"type\":\"bool\"}],\"payable\":false,\"stateMutability\":\"view\",\"type\":\"function\"},{\"constant\":false,\"inputs\":[],\"name\":\"disableDonation\",\"outputs\":[{\"name\":\"success\",\"type\":\"bool\"}],\"payable\":false,\"stateMutability\":\"nonpayable\",\"type\":\"function\"},{\"constant\":false,\"inputs\":[{\"name\":\"newOwner\",\"type\":\"address\"}],\"name\":\"transferOwnership\",\"outputs\":[],\"payable\":false,\"stateMutability\":\"nonpayable\",\"type\":\"function\"},{\"inputs\":[],\"payable\":false,\"stateMutability\":\"nonpayable\",\"type\":\"constructor\"},{\"payable\":true,\"stateMutability\":\"payable\",\"type\":\"fallback\"},{\"anonymous\":false,\"inputs\":[{\"indexed\":true,\"name\":\"from\",\"type\":\"address\"},{\"indexed\":true,\"name\":\"to\",\"type\":\"address\"},{\"indexed\":false,\"name\":\"value\",\"type\":\"uint256\"}],\"name\":\"Transfer\",\"type\":\"event\"}]","ContractName":"HelpingBlocksContract","CompilerVersion":"v0.4.24+commit.e67f0147","OptimizationUsed":"1","Runs":"200","ConstructorArguments":"","Library":"","SwarmSource":"bzzr://50546f6f79d20d8fdb4a181d77cd57a34d157eb730b88cf715b034e3edf85267"}]}