{"status":"1","message":"OK","result":[{"SourceCode":"contract test {\r\n\r\n        uint _multiplier;\r\n\r\n        constructor (uint multiplier) public {\r\n             _multiplier = multiplier;\r\n        }\r\n\r\n        function multiply(uint a) public view returns(uint d)  \r\n        {\r\n             return a * _multiplier;\r\n        }\r\n    }","ABI":"[{\"constant\":true,\"inputs\":[{\"name\":\"a\",\"type\":\"uint256\"}],\"name\":\"multiply\",\"outputs\":[{\"name\":\"d\",\"type\":\"uint256\"}],\"payable\":false,\"stateMutability\":\"view\",\"type\":\"function\"},{\"inputs\":[{\"name\":\"multiplier\",\"type\":\"uint256\"}],\"payable\":false,\"stateMutability\":\"nonpayable\",\"type\":\"constructor\"}]","ContractName":"test","CompilerVersion":"v0.4.24+commit.e67f0147","OptimizationUsed":"0","Runs":"200","ConstructorArguments":"0000000000000000000000000000000000000000000000000000000000000002","Library":"","SwarmSource":"bzzr://7331918eeb35c67b38843bb323f5bf951cf44bd8244ebfc72fadac788a7db8e9"}]}