{"status":"1","message":"OK","result":[{"SourceCode":"pragma solidity ^0.4.25;\r\n\r\ncontract G2X {\r\n\r\n    mapping (address => uint256) public balances;\r\n    mapping (address => mapping (address => uint256)) public allowed;\r\n    uint256 public sellPrice;\r\n    uint256 public buyPrice;\r\n    uint256 public numDecimalsBuyPrice;\r\n    uint256 public numDecimalsSellPrice;\r\n    string public name;                   \r\n    uint8 public decimals;                \r\n    string public symbol;                 \r\n    address public owner;\r\n    uint256 public totalSupply;\r\n\r\n    constructor () public {\r\n        balances[msg.sender] = 72313360000000000000000000;\r\n        totalSupply = 72313360000000000000000000;\r\n        name = \"GOW2X\";\r\n        decimals = 18;\r\n        symbol = \"G2X\";\r\n        owner = msg.sender;\r\n        sellPrice = 6;\r\n        numDecimalsSellPrice = 100000;\r\n        buyPrice = 6;\r\n        numDecimalsBuyPrice = 100000;\r\n    }\r\n\r\n    function recieveFunds() public payable {\r\n        emit ReciveFunds(msg.sender,msg.value);   \r\n    } \r\n    \r\n    function returnFunds(uint256 _value) public onlyOwner {\r\n        require (address (this).balance >= _value);\r\n        owner.transfer (_value);\r\n        emit ReturnFunds(msg.sender, _value);\r\n    }\r\n    \r\n    function getBalance() public view returns(uint256) { \r\n        return address(this).balance; \r\n    }    \r\n\r\n    modifier onlyOwner {\r\n        require(msg.sender == owner);\r\n        _;\r\n    }\r\n\r\n    function transferOwnership(address newOwner) public onlyOwner {\r\n        owner = newOwner;\r\n        emit TransferOwnership(newOwner); \r\n    }  \r\n\r\n    function setPrices(uint256 newSellPrice, uint256 newnumDecimalsSellPrice, uint256 newBuyPrice, uint256 newnumDecimalsBuyPrice) public onlyOwner {\r\n        sellPrice = newSellPrice;\r\n        buyPrice = newBuyPrice;\r\n        numDecimalsBuyPrice = newnumDecimalsBuyPrice;\r\n        numDecimalsSellPrice = newnumDecimalsSellPrice;\r\n        emit SetPrices(newSellPrice, newnumDecimalsSellPrice, newBuyPrice, newnumDecimalsBuyPrice);\r\n    }\r\n\r\n    function buy()public payable  returns (uint256 _value){\r\n        _value = (msg.value * numDecimalsBuyPrice) / buyPrice;\r\n        require(balances[this] >= _value);\r\n        balances[msg.sender] += _value;\r\n        balances[this] -= _value;\r\n        emit Buy(this, msg.sender, _value);\r\n        return _value;\r\n    }  \r\n\r\n    function sell(uint256 _value) public returns (uint256 revenue){\r\n        require(balances[msg.sender] >= _value);\r\n        balances[this] += _value;         \r\n        balances[msg.sender] -= _value;                  \r\n        revenue =   (_value * sellPrice) /numDecimalsSellPrice;\r\n        msg.sender.transfer(revenue);\r\n        emit Sell(msg.sender, this, _value);             \r\n        return revenue;                                   \r\n    }   \r\n\r\n    function transfer(address _to, uint256 _value) public returns (bool success) {\r\n        require (_to != (0x0));\r\n        require(balances[msg.sender] >= _value);\r\n        balances[msg.sender] -= _value;\r\n        balances[_to] += _value;\r\n        emit Transfer(msg.sender, _to, _value); \r\n        return true;\r\n    }\r\n\r\n    function transferFrom(address _from, address _to, uint256 _value) public returns (bool success) {\r\n        uint256 allowance = allowed[_from][msg.sender];\r\n        require (_to != (0x0));\r\n        require(balances[_from] >= _value && allowance >= _value);\r\n        balances[_to] += _value;\r\n        balances[_from] -= _value;\r\n        allowed[_from][msg.sender] -= _value;\r\n        emit Transfer(_from, _to, _value); \r\n        return true;\r\n    }\r\n\r\n    function balanceOf(address _owner) public view returns (uint256 balance) {\r\n        return balances[_owner];\r\n    }\r\n\r\n    function approve(address _spender, uint256 _value) public returns (bool success) {\r\n        allowed[msg.sender][_spender] = _value;\r\n        emit Approval(msg.sender, _spender, _value); \r\n        return true;\r\n    }\r\n\r\n    function allowance(address _owner, address _spender) public view returns (uint256 remaining) {\r\n        return allowed[_owner][_spender];\r\n    }\r\n \r\n    function burn(uint256 _value) public onlyOwner returns (bool success) {\r\n        require(balances[msg.sender] >= _value);   // Check if the sender has enough\r\n        balances[msg.sender] -= _value;            // Subtract from the sender\r\n        totalSupply -= _value;                      // Updates totalSupply\r\n        emit Burn(msg.sender, _value);\r\n        return true;\r\n    }\r\n\r\n    event Transfer(address indexed _from, address indexed _to, uint256 _value);\r\n    event Sell(address indexed _from, address indexed _to, uint256 _value);\r\n    event Buy(address indexed _from, address indexed _to, uint256 _value);\r\n    event Approval(address indexed _owner, address indexed _spender, uint256 _value);\r\n    event Burn(address indexed _from, uint256 value);\r\n    event SetPrices(uint256 newSellPrice, uint256 newnumDecimalsSellPrice, uint256 newBuyPrice, uint256 newnumDecimalsBuyPrice);\r\n    event TransferOwnership(address indexed newOwner);\r\n    event ReturnFunds(address indexed _from, uint256 _value);\r\n    event ReciveFunds(address indexed _from, uint256 _value);\r\n}","ABI":"[{\"constant\":true,\"inputs\":[],\"name\":\"name\",\"outputs\":[{\"name\":\"\",\"type\":\"string\"}],\"payable\":false,\"stateMutability\":\"view\",\"type\":\"function\"},{\"constant\":false,\"inputs\":[{\"name\":\"_spender\",\"type\":\"address\"},{\"name\":\"_value\",\"type\":\"uint256\"}],\"name\":\"approve\",\"outputs\":[{\"name\":\"success\",\"type\":\"bool\"}],\"payable\":false,\"stateMutability\":\"nonpayable\",\"type\":\"function\"},{\"constant\":true,\"inputs\":[],\"name\":\"getBalance\",\"outputs\":[{\"name\":\"\",\"type\":\"uint256\"}],\"payable\":false,\"stateMutability\":\"view\",\"type\":\"function\"},{\"constant\":true,\"inputs\":[],\"name\":\"totalSupply\",\"outputs\":[{\"name\":\"\",\"type\":\"uint256\"}],\"payable\":false,\"stateMutability\":\"view\",\"type\":\"function\"},{\"constant\":true,\"inputs\":[],\"name\":\"numDecimalsSellPrice\",\"outputs\":[{\"name\":\"\",\"type\":\"uint256\"}],\"payable\":false,\"stateMutability\":\"view\",\"type\":\"function\"},{\"constant\":false,\"inputs\":[{\"name\":\"_from\",\"type\":\"address\"},{\"name\":\"_to\",\"type\":\"address\"},{\"name\":\"_value\",\"type\":\"uint256\"}],\"name\":\"transferFrom\",\"outputs\":[{\"name\":\"success\",\"type\":\"bool\"}],\"payable\":false,\"stateMutability\":\"nonpayable\",\"type\":\"function\"},{\"constant\":true,\"inputs\":[{\"name\":\"\",\"type\":\"address\"}],\"name\":\"balances\",\"outputs\":[{\"name\":\"\",\"type\":\"uint256\"}],\"payable\":false,\"stateMutability\":\"view\",\"type\":\"function\"},{\"constant\":true,\"inputs\":[],\"name\":\"decimals\",\"outputs\":[{\"name\":\"\",\"type\":\"uint8\"}],\"payable\":false,\"stateMutability\":\"view\",\"type\":\"function\"},{\"constant\":false,\"inputs\":[{\"name\":\"_value\",\"type\":\"uint256\"}],\"name\":\"burn\",\"outputs\":[{\"name\":\"success\",\"type\":\"bool\"}],\"payable\":false,\"stateMutability\":\"nonpayable\",\"type\":\"function\"},{\"constant\":false,\"inputs\":[{\"name\":\"_value\",\"type\":\"uint256\"}],\"name\":\"returnFunds\",\"outputs\":[],\"payable\":false,\"stateMutability\":\"nonpayable\",\"type\":\"function\"},{\"constant\":true,\"inputs\":[],\"name\":\"sellPrice\",\"outputs\":[{\"name\":\"\",\"type\":\"uint256\"}],\"payable\":false,\"stateMutability\":\"view\",\"type\":\"function\"},{\"constant\":true,\"inputs\":[{\"name\":\"\",\"type\":\"address\"},{\"name\":\"\",\"type\":\"address\"}],\"name\":\"allowed\",\"outputs\":[{\"name\":\"\",\"type\":\"uint256\"}],\"payable\":false,\"stateMutability\":\"view\",\"type\":\"function\"},{\"constant\":true,\"inputs\":[{\"name\":\"_owner\",\"type\":\"address\"}],\"name\":\"balanceOf\",\"outputs\":[{\"name\":\"balance\",\"type\":\"uint256\"}],\"payable\":false,\"stateMutability\":\"view\",\"type\":\"function\"},{\"constant\":true,\"inputs\":[],\"name\":\"buyPrice\",\"outputs\":[{\"name\":\"\",\"type\":\"uint256\"}],\"payable\":false,\"stateMutability\":\"view\",\"type\":\"function\"},{\"constant\":true,\"inputs\":[],\"name\":\"owner\",\"outputs\":[{\"name\":\"\",\"type\":\"address\"}],\"payable\":false,\"stateMutability\":\"view\",\"type\":\"function\"},{\"constant\":true,\"inputs\":[],\"name\":\"symbol\",\"outputs\":[{\"name\":\"\",\"type\":\"string\"}],\"payable\":false,\"stateMutability\":\"view\",\"type\":\"function\"},{\"constant\":true,\"inputs\":[],\"name\":\"numDecimalsBuyPrice\",\"outputs\":[{\"name\":\"\",\"type\":\"uint256\"}],\"payable\":false,\"stateMutability\":\"view\",\"type\":\"function\"},{\"constant\":false,\"inputs\":[],\"name\":\"buy\",\"outputs\":[{\"name\":\"_value\",\"type\":\"uint256\"}],\"payable\":true,\"stateMutability\":\"payable\",\"type\":\"function\"},{\"constant\":false,\"inputs\":[{\"name\":\"_to\",\"type\":\"address\"},{\"name\":\"_value\",\"type\":\"uint256\"}],\"name\":\"transfer\",\"outputs\":[{\"name\":\"success\",\"type\":\"bool\"}],\"payable\":false,\"stateMutability\":\"nonpayable\",\"type\":\"function\"},{\"constant\":false,\"inputs\":[],\"name\":\"recieveFunds\",\"outputs\":[],\"payable\":true,\"stateMutability\":\"payable\",\"type\":\"function\"},{\"constant\":false,\"inputs\":[{\"name\":\"newSellPrice\",\"type\":\"uint256\"},{\"name\":\"newnumDecimalsSellPrice\",\"type\":\"uint256\"},{\"name\":\"newBuyPrice\",\"type\":\"uint256\"},{\"name\":\"newnumDecimalsBuyPrice\",\"type\":\"uint256\"}],\"name\":\"setPrices\",\"outputs\":[],\"payable\":false,\"stateMutability\":\"nonpayable\",\"type\":\"function\"},{\"constant\":true,\"inputs\":[{\"name\":\"_owner\",\"type\":\"address\"},{\"name\":\"_spender\",\"type\":\"address\"}],\"name\":\"allowance\",\"outputs\":[{\"name\":\"remaining\",\"type\":\"uint256\"}],\"payable\":false,\"stateMutability\":\"view\",\"type\":\"function\"},{\"constant\":false,\"inputs\":[{\"name\":\"_value\",\"type\":\"uint256\"}],\"name\":\"sell\",\"outputs\":[{\"name\":\"revenue\",\"type\":\"uint256\"}],\"payable\":false,\"stateMutability\":\"nonpayable\",\"type\":\"function\"},{\"constant\":false,\"inputs\":[{\"name\":\"newOwner\",\"type\":\"address\"}],\"name\":\"transferOwnership\",\"outputs\":[],\"payable\":false,\"stateMutability\":\"nonpayable\",\"type\":\"function\"},{\"inputs\":[],\"payable\":false,\"stateMutability\":\"nonpayable\",\"type\":\"constructor\"},{\"anonymous\":false,\"inputs\":[{\"indexed\":true,\"name\":\"_from\",\"type\":\"address\"},{\"indexed\":true,\"name\":\"_to\",\"type\":\"address\"},{\"indexed\":false,\"name\":\"_value\",\"type\":\"uint256\"}],\"name\":\"Transfer\",\"type\":\"event\"},{\"anonymous\":false,\"inputs\":[{\"indexed\":true,\"name\":\"_from\",\"type\":\"address\"},{\"indexed\":true,\"name\":\"_to\",\"type\":\"address\"},{\"indexed\":false,\"name\":\"_value\",\"type\":\"uint256\"}],\"name\":\"Sell\",\"type\":\"event\"},{\"anonymous\":false,\"inputs\":[{\"indexed\":true,\"name\":\"_from\",\"type\":\"address\"},{\"indexed\":true,\"name\":\"_to\",\"type\":\"address\"},{\"indexed\":false,\"name\":\"_value\",\"type\":\"uint256\"}],\"name\":\"Buy\",\"type\":\"event\"},{\"anonymous\":false,\"inputs\":[{\"indexed\":true,\"name\":\"_owner\",\"type\":\"address\"},{\"indexed\":true,\"name\":\"_spender\",\"type\":\"address\"},{\"indexed\":false,\"name\":\"_value\",\"type\":\"uint256\"}],\"name\":\"Approval\",\"type\":\"event\"},{\"anonymous\":false,\"inputs\":[{\"indexed\":true,\"name\":\"_from\",\"type\":\"address\"},{\"indexed\":false,\"name\":\"value\",\"type\":\"uint256\"}],\"name\":\"Burn\",\"type\":\"event\"},{\"anonymous\":false,\"inputs\":[{\"indexed\":false,\"name\":\"newSellPrice\",\"type\":\"uint256\"},{\"indexed\":false,\"name\":\"newnumDecimalsSellPrice\",\"type\":\"uint256\"},{\"indexed\":false,\"name\":\"newBuyPrice\",\"type\":\"uint256\"},{\"indexed\":false,\"name\":\"newnumDecimalsBuyPrice\",\"type\":\"uint256\"}],\"name\":\"SetPrices\",\"type\":\"event\"},{\"anonymous\":false,\"inputs\":[{\"indexed\":true,\"name\":\"newOwner\",\"type\":\"address\"}],\"name\":\"TransferOwnership\",\"type\":\"event\"},{\"anonymous\":false,\"inputs\":[{\"indexed\":true,\"name\":\"_from\",\"type\":\"address\"},{\"indexed\":false,\"name\":\"_value\",\"type\":\"uint256\"}],\"name\":\"ReturnFunds\",\"type\":\"event\"},{\"anonymous\":false,\"inputs\":[{\"indexed\":true,\"name\":\"_from\",\"type\":\"address\"},{\"indexed\":false,\"name\":\"_value\",\"type\":\"uint256\"}],\"name\":\"ReciveFunds\",\"type\":\"event\"}]","ContractName":"G2X","CompilerVersion":"v0.4.25+commit.59dbf8f1","OptimizationUsed":"0","Runs":"200","ConstructorArguments":"","Library":"","SwarmSource":"bzzr://12eb9ac8e2c1cb7bd78fb4b2453b8f0984d57c9c1de69d2fbdc84b66610ca3c7"}]}