{"status":"1","message":"OK","result":[{"SourceCode":"pragma solidity ^0.4.13;\r\n\r\ncontract DSAuthority {\r\n    function canCall(\r\n        address src, address dst, bytes4 sig\r\n    ) public view returns (bool);\r\n}\r\n\r\ncontract DSAuthEvents {\r\n    event LogSetAuthority (address indexed authority);\r\n    event LogSetOwner     (address indexed owner);\r\n}\r\n\r\ncontract DSAuth is DSAuthEvents {\r\n    DSAuthority  public  authority;\r\n    address      public  owner;\r\n\r\n    function DSAuth() public {\r\n        owner = msg.sender;\r\n        LogSetOwner(msg.sender);\r\n    }\r\n\r\n    function setOwner(address owner_)\r\n        public\r\n        auth\r\n    {\r\n        owner = owner_;\r\n        LogSetOwner(owner);\r\n    }\r\n\r\n    function setAuthority(DSAuthority authority_)\r\n        public\r\n        auth\r\n    {\r\n        authority = authority_;\r\n        LogSetAuthority(authority);\r\n    }\r\n\r\n    modifier auth {\r\n        require(isAuthorized(msg.sender, msg.sig));\r\n        _;\r\n    }\r\n\r\n    function isAuthorized(address src, bytes4 sig) internal view returns (bool) {\r\n        if (src == address(this)) {\r\n            return true;\r\n        } else if (src == owner) {\r\n            return true;\r\n        } else if (authority == DSAuthority(0)) {\r\n            return false;\r\n        } else {\r\n            return authority.canCall(src, this, sig);\r\n        }\r\n    }\r\n}\r\n\r\ncontract DSNote {\r\n    event LogNote(\r\n        bytes4   indexed  sig,\r\n        address  indexed  guy,\r\n        bytes32  indexed  foo,\r\n        bytes32  indexed  bar,\r\n        uint              wad,\r\n        bytes             fax\r\n    ) anonymous;\r\n\r\n    modifier note {\r\n        bytes32 foo;\r\n        bytes32 bar;\r\n\r\n        assembly {\r\n            foo := calldataload(4)\r\n            bar := calldataload(36)\r\n        }\r\n\r\n        LogNote(msg.sig, msg.sender, foo, bar, msg.value, msg.data);\r\n\r\n        _;\r\n    }\r\n}\r\n\r\ncontract DSStop is DSNote, DSAuth {\r\n\r\n    bool public stopped;\r\n\r\n    modifier stoppable {\r\n        require(!stopped);\r\n        _;\r\n    }\r\n    function stop() public auth note {\r\n        stopped = true;\r\n    }\r\n    function start() public auth note {\r\n        stopped = false;\r\n    }\r\n\r\n}\r\n\r\ncontract TokenTransferGuard {\r\n    function onTokenTransfer(address _from, address _to, uint _amount) public returns (bool);\r\n}\r\n\r\ncontract FrozenGuard is DSStop, TokenTransferGuard {\r\n\r\n    function FrozenGuard()\r\n    {\r\n    }\r\n\r\n    function onTokenTransfer(address _from, address _to, uint _amount) public returns (bool)\r\n    {\r\n        // 2018-04-27 04:00 GMT\r\n        if ( !stopped && block.timestamp >= 1524801600)\r\n        {\r\n            return false;\r\n        }\r\n        \r\n        return true;\r\n    }\r\n}","ABI":"[{\"constant\":false,\"inputs\":[],\"name\":\"stop\",\"outputs\":[],\"payable\":false,\"stateMutability\":\"nonpayable\",\"type\":\"function\"},{\"constant\":false,\"inputs\":[{\"name\":\"owner_\",\"type\":\"address\"}],\"name\":\"setOwner\",\"outputs\":[],\"payable\":false,\"stateMutability\":\"nonpayable\",\"type\":\"function\"},{\"constant\":false,\"inputs\":[{\"name\":\"_from\",\"type\":\"address\"},{\"name\":\"_to\",\"type\":\"address\"},{\"name\":\"_amount\",\"type\":\"uint256\"}],\"name\":\"onTokenTransfer\",\"outputs\":[{\"name\":\"\",\"type\":\"bool\"}],\"payable\":false,\"stateMutability\":\"nonpayable\",\"type\":\"function\"},{\"constant\":true,\"inputs\":[],\"name\":\"stopped\",\"outputs\":[{\"name\":\"\",\"type\":\"bool\"}],\"payable\":false,\"stateMutability\":\"view\",\"type\":\"function\"},{\"constant\":false,\"inputs\":[{\"name\":\"authority_\",\"type\":\"address\"}],\"name\":\"setAuthority\",\"outputs\":[],\"payable\":false,\"stateMutability\":\"nonpayable\",\"type\":\"function\"},{\"constant\":true,\"inputs\":[],\"name\":\"owner\",\"outputs\":[{\"name\":\"\",\"type\":\"address\"}],\"payable\":false,\"stateMutability\":\"view\",\"type\":\"function\"},{\"constant\":false,\"inputs\":[],\"name\":\"start\",\"outputs\":[],\"payable\":false,\"stateMutability\":\"nonpayable\",\"type\":\"function\"},{\"constant\":true,\"inputs\":[],\"name\":\"authority\",\"outputs\":[{\"name\":\"\",\"type\":\"address\"}],\"payable\":false,\"stateMutability\":\"view\",\"type\":\"function\"},{\"inputs\":[],\"payable\":false,\"stateMutability\":\"nonpayable\",\"type\":\"constructor\"},{\"anonymous\":false,\"inputs\":[{\"indexed\":true,\"name\":\"authority\",\"type\":\"address\"}],\"name\":\"LogSetAuthority\",\"type\":\"event\"},{\"anonymous\":false,\"inputs\":[{\"indexed\":true,\"name\":\"owner\",\"type\":\"address\"}],\"name\":\"LogSetOwner\",\"type\":\"event\"},{\"anonymous\":true,\"inputs\":[{\"indexed\":true,\"name\":\"sig\",\"type\":\"bytes4\"},{\"indexed\":true,\"name\":\"guy\",\"type\":\"address\"},{\"indexed\":true,\"name\":\"foo\",\"type\":\"bytes32\"},{\"indexed\":true,\"name\":\"bar\",\"type\":\"bytes32\"},{\"indexed\":false,\"name\":\"wad\",\"type\":\"uint256\"},{\"indexed\":false,\"name\":\"fax\",\"type\":\"bytes\"}],\"name\":\"LogNote\",\"type\":\"event\"}]","ContractName":"FrozenGuard","CompilerVersion":"v0.4.17+commit.bdeb9e52","OptimizationUsed":"1","Runs":"200","ConstructorArguments":"","Library":"","SwarmSource":"bzzr://cb27cadf3f66c4c7e63bff70471bb20e1f882a9ab045965a6df561ec29051fb1"}]}