{"status":"1","message":"OK","result":[{"SourceCode":"pragma solidity ^0.4.21;\r\n\r\ncontract owned {\r\n    address public owner;\r\n\r\n    function owned() public {\r\n        owner = msg.sender;\r\n    }\r\n\r\n    modifier onlyOwner {\r\n        if(msg.sender != owner) revert();\r\n        _;\r\n    }\r\n\r\n    function tranferOwnership(address _newOwner) public onlyOwner() {\r\n        owner = _newOwner;\r\n    }\r\n}\r\n\r\ncontract Token {\r\n    function mintTokens(address _atAddress, uint256 _amount) public;\r\n}\r\n\r\ncontract TokenGeneration is owned {\r\n    Token token;\r\n\r\n    function setToken(address _token) public onlyOwner {\r\n        token = Token(_token);\r\n    }\r\n\r\n    function generateTokens(address[] _addresses, uint256[] _amount) public onlyOwner {\r\n        for(uint256 i = 0; i < _addresses.length; i++) {\r\n            token.mintTokens(_addresses[i], _amount[i]);\r\n        }\r\n    }\r\n\r\n    function getToken() public constant returns(address) {\r\n        return address(token);\r\n    }\r\n}","ABI":"[{\"constant\":false,\"inputs\":[{\"name\":\"_token\",\"type\":\"address\"}],\"name\":\"setToken\",\"outputs\":[],\"payable\":false,\"stateMutability\":\"nonpayable\",\"type\":\"function\"},{\"constant\":true,\"inputs\":[],\"name\":\"getToken\",\"outputs\":[{\"name\":\"\",\"type\":\"address\"}],\"payable\":false,\"stateMutability\":\"view\",\"type\":\"function\"},{\"constant\":false,\"inputs\":[{\"name\":\"_newOwner\",\"type\":\"address\"}],\"name\":\"tranferOwnership\",\"outputs\":[],\"payable\":false,\"stateMutability\":\"nonpayable\",\"type\":\"function\"},{\"constant\":true,\"inputs\":[],\"name\":\"owner\",\"outputs\":[{\"name\":\"\",\"type\":\"address\"}],\"payable\":false,\"stateMutability\":\"view\",\"type\":\"function\"},{\"constant\":false,\"inputs\":[{\"name\":\"_addresses\",\"type\":\"address[]\"},{\"name\":\"_amount\",\"type\":\"uint256[]\"}],\"name\":\"generateTokens\",\"outputs\":[],\"payable\":false,\"stateMutability\":\"nonpayable\",\"type\":\"function\"}]","ContractName":"TokenGeneration","CompilerVersion":"v0.4.21+commit.dfe3193c","OptimizationUsed":"0","Runs":"200","ConstructorArguments":"","Library":"","LicenseType":"MIT","SwarmSource":"bzzr://26893a09ad3e72df1636a1bbf3e923bfdda5aa029c9da3d5dca71f69b2dc5e27"}]}