{"status":"1","message":"OK","result":[{"SourceCode":"pragma solidity ^0.4.24;\r\n\r\ncontract Kiwiana {\r\n    address public owner;\r\n    mapping (address => uint) public payments;\r\n    mapping (address => string) public allergies;\r\n    address public chris = 0xC369B30c8eC960260631E20081A32e4c61E5Ea9d;\r\n\r\n    constructor() public {\r\n        owner = msg.sender;\r\n    }\r\n\r\n    modifier onlyOwner() {\r\n        require(msg.sender == owner);\r\n        _;\r\n    }\r\n\r\n    function () external payable {\r\n        register(msg.sender);\r\n    }\r\n\r\n    function register(address _attendee) public payable returns(bool) {\r\n        uint weiAmount = msg.value;\r\n        if(weiAmount >= 100000000000000000) {\r\n            payments[_attendee] = weiAmount;\r\n            return true;\r\n        }\r\n        else {\r\n            // you didn't pay enough, so we're just swallowing how much you spent\r\n            return false;\r\n        }\r\n    }\r\n\r\n    function isEatingAndDrinking(address __attendee) public view returns(bool) {\r\n        if(payments[__attendee] >= 150000000000000000) {\r\n            return true;\r\n        }\r\n        return false;\r\n    }\r\n\r\n    function isEating(address __attendee) public view returns(bool) {\r\n        if(payments[__attendee] >= 100000000000000000) {\r\n            return true;\r\n        }\r\n        return false;\r\n    }\r\n\r\n    function allergy(string _description) public payable returns(bool) {\r\n        if(payments[msg.sender] >= 100000000000000000) {\r\n            // you paid so we care about your allergies\r\n            allergies[msg.sender] = _description;\r\n            return true;\r\n        }\r\n        return false;\r\n    }\r\n\r\n    function giveMeBackMyMoney() public onlyOwner {\r\n        //send all money to chris\r\n        chris.transfer(address(this).balance);\r\n    }\r\n}","ABI":"[{\"constant\":true,\"inputs\":[{\"name\":\"__attendee\",\"type\":\"address\"}],\"name\":\"isEatingAndDrinking\",\"outputs\":[{\"name\":\"\",\"type\":\"bool\"}],\"payable\":false,\"stateMutability\":\"view\",\"type\":\"function\"},{\"constant\":false,\"inputs\":[{\"name\":\"_attendee\",\"type\":\"address\"}],\"name\":\"register\",\"outputs\":[{\"name\":\"\",\"type\":\"bool\"}],\"payable\":true,\"stateMutability\":\"payable\",\"type\":\"function\"},{\"constant\":false,\"inputs\":[{\"name\":\"_description\",\"type\":\"string\"}],\"name\":\"allergy\",\"outputs\":[{\"name\":\"\",\"type\":\"bool\"}],\"payable\":true,\"stateMutability\":\"payable\",\"type\":\"function\"},{\"constant\":true,\"inputs\":[{\"name\":\"\",\"type\":\"address\"}],\"name\":\"allergies\",\"outputs\":[{\"name\":\"\",\"type\":\"string\"}],\"payable\":false,\"stateMutability\":\"view\",\"type\":\"function\"},{\"constant\":false,\"inputs\":[],\"name\":\"giveMeBackMyMoney\",\"outputs\":[],\"payable\":false,\"stateMutability\":\"nonpayable\",\"type\":\"function\"},{\"constant\":true,\"inputs\":[],\"name\":\"chris\",\"outputs\":[{\"name\":\"\",\"type\":\"address\"}],\"payable\":false,\"stateMutability\":\"view\",\"type\":\"function\"},{\"constant\":true,\"inputs\":[],\"name\":\"owner\",\"outputs\":[{\"name\":\"\",\"type\":\"address\"}],\"payable\":false,\"stateMutability\":\"view\",\"type\":\"function\"},{\"constant\":true,\"inputs\":[{\"name\":\"__attendee\",\"type\":\"address\"}],\"name\":\"isEating\",\"outputs\":[{\"name\":\"\",\"type\":\"bool\"}],\"payable\":false,\"stateMutability\":\"view\",\"type\":\"function\"},{\"constant\":true,\"inputs\":[{\"name\":\"\",\"type\":\"address\"}],\"name\":\"payments\",\"outputs\":[{\"name\":\"\",\"type\":\"uint256\"}],\"payable\":false,\"stateMutability\":\"view\",\"type\":\"function\"},{\"inputs\":[],\"payable\":false,\"stateMutability\":\"nonpayable\",\"type\":\"constructor\"},{\"payable\":true,\"stateMutability\":\"payable\",\"type\":\"fallback\"}]","ContractName":"Kiwiana","CompilerVersion":"v0.4.24+commit.e67f0147","OptimizationUsed":"0","Runs":"200","ConstructorArguments":"","Library":"","SwarmSource":"bzzr://69f3650f7e05f3a919aaab13529406dcaa38650d7fba056a107e60b391a51ab7"}]}